handshake/.version
handshake/Exporters/Template.xlsx
handshake/Exporters/__init__.py
handshake/Exporters/excel_exporter.py
handshake/Exporters/exported_data.py
handshake/Exporters/exporter.py
handshake/Exporters/html_reporter.py
handshake/Exporters/json_exporter.py
handshake/__init__.py
handshake/reporters/__init__.py
handshake/reporters/markers.py
handshake/reporters/pytest_hooks.py
handshake/reporters/pytest_reporter.py
handshake/reporters/reporter.py
handshake/services/CommandLine/__init__.py
handshake/services/CommandLine/_init.py
handshake/services/CommandLine/center.py
handshake/services/DBService/__init__.py
handshake/services/DBService/lifecycle.py
handshake/services/DBService/merge.py
handshake/services/DBService/migrator.py
handshake/services/DBService/models/__init__.py
handshake/services/DBService/models/attachmentBase.py
handshake/services/DBService/models/config_base.py
handshake/services/DBService/models/dynamic_base.py
handshake/services/DBService/models/enums.py
handshake/services/DBService/models/result_base.py
handshake/services/DBService/models/static_base.py
handshake/services/DBService/models/types.py
handshake/services/DBService/sanic_free_shared.py
handshake/services/DBService/scripts/bump-v10.sql
handshake/services/DBService/scripts/bump-v11.sql
handshake/services/DBService/scripts/bump-v12.sql
handshake/services/DBService/scripts/bump-v13.sql
handshake/services/DBService/scripts/bump-v14.sql
handshake/services/DBService/scripts/bump-v15.sql
handshake/services/DBService/scripts/bump-v16.sql
handshake/services/DBService/scripts/bump-v8.sql
handshake/services/DBService/scripts/bump-v9.sql
handshake/services/DBService/scripts/revert-v10.sql
handshake/services/DBService/scripts/revert-v11.sql
handshake/services/DBService/scripts/revert-v12.sql
handshake/services/DBService/scripts/revert-v13.sql
handshake/services/DBService/scripts/revert-v14.sql
handshake/services/DBService/scripts/revert-v15.sql
handshakes-0.10.2.dist-info/LICENSE
handshakes-0.10.2.dist-info/METADATA
handshakes-0.10.2.dist-info/WHEEL
handshakes-0.10.2.dist-info/entry_points.txt
handshakes-0.10.2.dist-info/RECORD
